pathmod/__init__.py
pathmod/__main__.py
pathmod/pathutils.py
pathmod/refresh.py
pathmod/cli/__init__.py
pathmod/cli/commands.py
pathmod-0.1.0.dist-info/LICENSE
pathmod-0.1.0.dist-info/METADATA
pathmod-0.1.0.dist-info/WHEEL
pathmod-0.1.0.dist-info/entry_points.txt
pathmod-0.1.0.dist-info/top_level.txt
pathmod-0.1.0.dist-info/RECORD
