Metadata-Version: 2.1
Name: pathmod
Version: 0.1.0
Summary: CLI tool for easily modifying the PATH (persistently) on Windows.
Home-page: UNKNOWN
Author: Sam McCormack
Author-email: cabbagedevelopment@gmail.com
License: UNKNOWN
Project-URL: Source, https://github.com/CabbageDevelopment/pathmod
Keywords: cli tool path windows
Platform: UNKNOWN
Classifier: Development Status :: 4 - Beta
Classifier: Intended Audience :: Developers
Classifier: License :: OSI Approved :: MIT License
Requires-Python: ~=3.6
Requires-Dist: click (==7.1.2)
